{
  "summary": {
    "title": "TenantUserManagement",
    "description": "租户用户管理"
  },
  "detail": {
    "contributors": [],
    "diagrams": [
      {
        "title": "邀请用户加入租户",
        "thumbnail": "./public/content/images/thumbnail.jpg",
        "id": 0,
        "diagramJson": {
          "cells": [
            {
              "type": "tm.Actor",
              "size": {
                "width": 160,
                "height": 80
              },
              "position": {
                "x": 50,
                "y": 50
              },
              "angle": 0,
              "id": "538bd14f-2fb7-4c2d-8649-8130f3ca43d6",
              "z": 1,
              "hasOpenThreats": false,
              "attrs": {
                ".element-shape": {
                  "class": "element-shape hasNoOpenThreats isInScope"
                },
                "text": {
                  "text": "actor 0"
                },
                ".element-text": {
                  "class": "element-text hasNoOpenThreats isInScope"
                }
              }
            }
          ]
        },
        "size": {
          "height": 590,
          "width": 790
        }
      }
    ]
  }
}